bdx_work_shop/__init__.py
bdx_work_shop/convert_img.py
bdx_work_shop/artists/__init__.py
bdx_work_shop/artists/basic.py
bdx_work_shop/artists/cmd_midi_music.py
bdx_work_shop/artists/map_art.py
bdx_work_shop/canvas/__init__.py
bdx_work_shop/canvas/blocks.py
bdx_work_shop/canvas/canvas.py
bdx_work_shop/canvas/decode_bdx.py
bdx_work_shop/canvas/encode_bdx.py
bdx_work_shop/canvas/ir.py
bdx_work_shop/canvas/irio.py
bdx_work_shop-0.0.10.dist-info/LICENSE.txt
bdx_work_shop-0.0.10.dist-info/METADATA
bdx_work_shop-0.0.10.dist-info/WHEEL
bdx_work_shop-0.0.10.dist-info/top_level.txt
bdx_work_shop-0.0.10.dist-info/RECORD
