Metadata-Version: 2.1
Name: bdx-work-shop
Version: 0.0.10
Summary: BDXWorkShop: 以稀疏矩阵为核心的 minecraft bdx 文件制作工具
Home-page: https://gitee.com/cma-2401pt/bdx-work-shop
Author: 2401pt,去幻想乡的老art
Author-email: 121980156@qq.com
Classifier: Programming Language :: Python :: 3
Classifier: License :: OSI Approved :: MIT License
Classifier: Operating System :: OS Independent
Requires-Python: >=3.6
License-File: LICENSE.txt
Requires-Dist: numpy
Requires-Dist: numba
Requires-Dist: brotli
Requires-Dist: requests
Requires-Dist: mido
Requires-Dist: pillow
